{"cameraMode":{"drawMode":0,"name":"Shaded","section":"Shading Mode"},"sceneLighting":true,"audioPlay":false,"sceneViewState":{"m_AlwaysRefresh":false,"showFog":true,"showSkybox":true,"showFlares":true,"showImageEffects":true,"showParticleSystems":true,"showVisualEffectGraphs":true,"m_FxEnabled":false},"in2DMode":false,"pivot":{"x":2.924938440322876,"y":23.16969871520996,"z":-32.20266342163086},"rotation":{"x":0.001831074827350676,"y":-0.9750409126281738,"z":0.012521627359092236,"w":0.22407114505767823},"size":10.0,"orthographic":false}